apihub_client/__init__.py
apihub_client/client.py
apihub_client/doc_splitter.py
apihub_client/generic_client.py
apihub_python_client-0.2.1.dist-info/METADATA
apihub_python_client-0.2.1.dist-info/WHEEL
apihub_python_client-0.2.1.dist-info/licenses/LICENSE
apihub_python_client-0.2.1.dist-info/RECORD
