Metadata-Version: 2.4
Name: apihub-python-client
Version: 0.2.1
Summary: A dynamic, extensible Python client for the APIHUB service supporting any APIs following the extract → status → retrieve pattern
Project-URL: Homepage, https://github.com/Zipstack/apihub-python-client
Project-URL: Documentation, https://github.com/Zipstack/apihub-python-clien
Project-URL: Repository, https://github.com/Zipstack/apihub-python-client
Project-URL: Bug Tracker, https://github.com/Zipstack/apihub-python-client/issues
Author-email: Unstract Team <support@unstract.com>
License-File: LICENSE
Classifier: Development Status :: 3 - Alpha
Classifier: Intended Audience :: Developers
Classifier: License :: OSI Approved :: MIT License
Classifier: Operating System :: OS Independent
Classifier: Programming Language :: Python :: 3
Classifier: Programming Language :: Python :: 3.12
Classifier: Topic :: Internet :: WWW/HTTP :: HTTP Servers
Classifier: Topic :: Software Development :: Libraries :: Python Modules
Requires-Python: >=3.12
Requires-Dist: httpx>=0.24.0
Requires-Dist: pydantic>=2.0.0
Requires-Dist: python-dotenv
Requires-Dist: requests>=2.28.0
Requires-Dist: tenacity>=8.0.0
Requires-Dist: typing-extensions>=4.0.0
Provides-Extra: async
Requires-Dist: aiofiles>=22.0.0; extra == 'async'
Requires-Dist: aiohttp>=3.8.0; extra == 'async'
Provides-Extra: dev
Requires-Dist: mypy>=1.0.0; extra == 'dev'
Requires-Dist: pre-commit>=3.0.0; extra == 'dev'
Requires-Dist: pytest-asyncio>=0.21.0; extra == 'dev'
Requires-Dist: pytest-cov>=4.0.0; extra == 'dev'
Requires-Dist: pytest>=7.0.0; extra == 'dev'
Requires-Dist: python-dotenv>=1.0.0; extra == 'dev'
Requires-Dist: ruff>=0.1.0; extra == 'dev'
Provides-Extra: docs
Requires-Dist: myst-parser>=0.18.0; extra == 'docs'
Requires-Dist: sphinx-autodoc-typehints>=1.19.0; extra == 'docs'
Requires-Dist: sphinx-rtd-theme>=1.2.0; extra == 'docs'
Requires-Dist: sphinx>=6.0.0; extra == 'docs'
Provides-Extra: test
Requires-Dist: pytest-asyncio>=0.21.0; extra == 'test'
Requires-Dist: pytest-cov>=4.0.0; extra == 'test'
Requires-Dist: pytest>=7.0.0; extra == 'test'
Requires-Dist: python-dotenv>=1.0.0; extra == 'test'
